py3odb/__init__.py
py3odb/connection.py
py3odb/cursor.py
py3odb/error.py
py3odb/odbql.py
py3odb/reader.py
py3odb/row.py
py3odb/util.py
py3odb/cli/__init__.py
py3odb/cli/command.py
py3odb/cli/dump.py
py3odb/cli/geopoints.py
py3odb/cli/main.py
py3odb/cli/query.py
py3odb/constants/__init__.py
py3odb/constants/varno.py
tests/__init__.py
tests/conftest.py
tests/context.py
tests/test_connection.py
tests/integration/__init__.py
tests/integration/conftest.py
tests/integration/test_errmsg.py
tests/integration/test_geopoints.py
tests/integration/test_insert_select.py
tests/integration/test_read_sample.py
tests/integration/test_reader.py
tests/integration/test_row.py
tests/unit/__init__.py
tests/unit/test_connection.py
tests/unit/test_cursor.py
tests/unit/test_odbql.py
tests/unit/test_row.py
tests/unit/cli/__init__.py
tests/unit/cli/conftest.py
tests/unit/cli/test_command.py
tests/unit/cli/test_dump.py
tests/unit/cli/test_geopoints.py
tests/unit/cli/test_main.py
tests/unit/cli/test_query.py
tests/unit/constants/__init__.py
tests/unit/constants/test_varno.py
py3odb-0.3.dist-info/LICENSE.md
py3odb-0.3.dist-info/METADATA
py3odb-0.3.dist-info/WHEEL
py3odb-0.3.dist-info/entry_points.txt
py3odb-0.3.dist-info/top_level.txt
py3odb-0.3.dist-info/RECORD
