Metadata-Version: 2.1
Name: py3odb
Version: 0.3
Summary: Python 3.6+ compatible interface to ECMWF's ODB API
Home-page: https://github.com/opus49/py3odb
Author: Mike Puskar
Author-email: puskar49@gmail.com
License: MIT
Project-URL: Documentation, https://py3odb.readthedocs.io
Platform: UNKNOWN
Classifier: Intended Audience :: Developers
Classifier: Intended Audience :: Science/Research
Classifier: License :: OSI Approved :: MIT License
Classifier: Operating System :: POSIX
Classifier: Programming Language :: Python :: 3.6
Requires-Python: >=3.6
